{
  "index": {
    "links": {
      "/": [
        {
          "source": "/",
          "target": "/notes/Polly-Labs",
          "text": "notes/Polly Labs"
        },
        {
          "source": "/",
          "target": "/notes/FoodCo",
          "text": "notes/FoodCo"
        },
        {
          "source": "/",
          "target": "/notes/Repurposing-Technology",
          "text": "notes/Repurposing Technology"
        },
        {
          "source": "/",
          "target": "/notes/Joblio",
          "text": "notes/Joblio"
        },
        {
          "source": "/",
          "target": "/google",
          "text": "google"
        },
        {
          "source": "/",
          "target": "/notes/People",
          "text": "notes/People"
        },
        {
          "source": "/",
          "target": "/family",
          "text": "family"
        },
        {
          "source": "/",
          "target": "/relationship",
          "text": "relationship"
        },
        {
          "source": "/",
          "target": "/friends",
          "text": "friends"
        },
        {
          "source": "/",
          "target": "/notes/cooking",
          "text": "notes/cooking"
        },
        {
          "source": "/",
          "target": "/notes/Fitness",
          "text": "notes/Fitness"
        },
        {
          "source": "/",
          "target": "/music",
          "text": "music"
        },
        {
          "source": "/",
          "target": "/literature",
          "text": "literature"
        },
        {
          "source": "/",
          "target": "/film",
          "text": "film"
        },
        {
          "source": "/",
          "target": "/content",
          "text": "content"
        },
        {
          "source": "/",
          "target": "/notes/My-Obsidian-Methodology",
          "text": "notes/My Obsidian Methodology"
        },
        {
          "source": "/",
          "target": "/notes/roots",
          "text": "notes/roots"
        },
        {
          "source": "/",
          "target": "/moc",
          "text": "moc"
        }
      ],
      "/2023-08-17": [
        {
          "source": "/2023-08-17",
          "target": "/notes/raw",
          "text": "notes/raw"
        }
      ],
      "/2023-08-18": [
        {
          "source": "/2023-08-18",
          "target": "/notes/raw",
          "text": "notes/raw"
        }
      ],
      "/202308181153": [
        {
          "source": "/202308181153",
          "target": "/notes/raw",
          "text": "notes/raw"
        }
      ],
      "/Ambrook": [
        {
          "source": "/Ambrook",
          "target": "/notes/raw",
          "text": "notes/raw"
        }
      ],
      "/Bold-Salt-Lick": [
        {
          "source": "/Bold-Salt-Lick",
          "target": "/notes/raw",
          "text": "notes/raw"
        }
      ],
      "/CSA": [
        {
          "source": "/CSA",
          "target": "/notes/raw",
          "text": "notes/raw"
        }
      ],
      "/Climate-Risk-on-Supply-Chain": [
        {
          "source": "/Climate-Risk-on-Supply-Chain",
          "target": "/notes/raw",
          "text": "notes/raw"
        }
      ],
      "/Content-List": [
        {
          "source": "/Content-List",
          "target": "/notes/raw",
          "text": "notes/raw"
        },
        {
          "source": "/Content-List",
          "target": "/moc",
          "text": "moc"
        }
      ],
      "/Conventional-vs-Controlled-Environment-Agriculture-Supply-Chains": [
        {
          "source": "/Conventional-vs-Controlled-Environment-Agriculture-Supply-Chains",
          "target": "/notes/raw",
          "text": "notes/raw"
        },
        {
          "source": "/Conventional-vs-Controlled-Environment-Agriculture-Supply-Chains",
          "target": "/notes/agriculture",
          "text": "notes/agriculture"
        }
      ],
      "/Farmers-Market-Management": [
        {
          "source": "/Farmers-Market-Management",
          "target": "/notes/raw",
          "text": "notes/raw"
        }
      ],
      "/Fitness": [
        {
          "source": "/Fitness",
          "target": "/notes/raw",
          "text": "notes/raw"
        },
        {
          "source": "/Fitness",
          "target": "/https//www.hybridcalisthenics.com/programshttps//www.hybridcalisthenics.com/programs",
          "text": "hybrid calisthenics"
        }
      ],
      "/Food-Hub": [
        {
          "source": "/Food-Hub",
          "target": "/notes/raw",
          "text": "notes/raw"
        }
      ],
      "/Food4All": [
        {
          "source": "/Food4All",
          "target": "/notes/raw",
          "text": "notes/raw"
        }
      ],
      "/FoodCo": [
        {
          "source": "/FoodCo",
          "target": "/notes/Polly-Labs",
          "text": "notes/Polly Labs"
        },
        {
          "source": "/FoodCo",
          "target": "/notes/FoodCo-Competitor-Analysis",
          "text": "notes/FoodCo Competitor Analysis"
        },
        {
          "source": "/FoodCo",
          "target": "/notes/FoodCo-Distributor-Analysis",
          "text": "notes/FoodCo Distributor Analysis"
        },
        {
          "source": "/FoodCo",
          "target": "/notes/FoodCo-Price-Analysis",
          "text": "notes/FoodCo Price Analysis"
        },
        {
          "source": "/FoodCo",
          "target": "/notes/FoodCo-Farmer-Marketing-Analysis",
          "text": "notes/FoodCo Farmer Marketing Analysis"
        },
        {
          "source": "/FoodCo",
          "target": "/notes/FoodCo-Customer-Analysis",
          "text": "notes/FoodCo Customer Analysis"
        },
        {
          "source": "/FoodCo",
          "target": "/notes/CSA",
          "text": "notes/CSA"
        },
        {
          "source": "/FoodCo",
          "target": "/moc",
          "text": "moc"
        }
      ],
      "/FoodCo-Competitor-Analysis": [
        {
          "source": "/FoodCo-Competitor-Analysis",
          "target": "/notes/Seven-Suns",
          "text": "notes/Seven Suns"
        },
        {
          "source": "/FoodCo-Competitor-Analysis",
          "target": "/notes/Barn2Door",
          "text": "notes/Barn2Door"
        },
        {
          "source": "/FoodCo-Competitor-Analysis",
          "target": "/notes/Bold-Salt-Lick",
          "text": "notes/Bold Salt Lick"
        },
        {
          "source": "/FoodCo-Competitor-Analysis",
          "target": "/notes/Eat-From-Farms",
          "text": "notes/Eat From Farms"
        },
        {
          "source": "/FoodCo-Competitor-Analysis",
          "target": "/notes/Food4All",
          "text": "notes/Food4All"
        },
        {
          "source": "/FoodCo-Competitor-Analysis",
          "target": "/Meicai",
          "text": "Meicai"
        },
        {
          "source": "/FoodCo-Competitor-Analysis",
          "target": "/notes/Local-Orbit",
          "text": "notes/Local Orbit"
        },
        {
          "source": "/FoodCo-Competitor-Analysis",
          "target": "/notes/Ambrook",
          "text": "notes/Ambrook"
        },
        {
          "source": "/FoodCo-Competitor-Analysis",
          "target": "/notes/Local-Food-Marketplace",
          "text": "notes/Local Food Marketplace"
        },
        {
          "source": "/FoodCo-Competitor-Analysis",
          "target": "/notes/Foraged",
          "text": "notes/Foraged"
        }
      ],
      "/FoodCo-Customer-Analysis": [
        {
          "source": "/FoodCo-Customer-Analysis",
          "target": "/notes/raw",
          "text": "notes/raw"
        }
      ],
      "/FoodCo-Distributor-Analysis": [
        {
          "source": "/FoodCo-Distributor-Analysis",
          "target": "/notes/raw",
          "text": "notes/raw"
        },
        {
          "source": "/FoodCo-Distributor-Analysis",
          "target": "/notes/Red-Tomato-Food-Hub",
          "text": "notes/Red Tomato Food Hub"
        },
        {
          "source": "/FoodCo-Distributor-Analysis",
          "target": "/notes/Food-Hub",
          "text": "notes/Food Hub"
        },
        {
          "source": "/FoodCo-Distributor-Analysis",
          "target": "/notes/Red-Tomato-Food-Hub",
          "text": "notes/Red Tomato Food Hub"
        }
      ],
      "/FoodCo-Farmer-Marketing-Analysis": [
        {
          "source": "/FoodCo-Farmer-Marketing-Analysis",
          "target": "/notes/raw",
          "text": "notes/raw"
        }
      ],
      "/FoodCo-Price-Analysis": [
        {
          "source": "/FoodCo-Price-Analysis",
          "target": "/notes/raw",
          "text": "notes/raw"
        }
      ],
      "/Foraged": [
        {
          "source": "/Foraged",
          "target": "/notes/raw",
          "text": "notes/raw"
        }
      ],
      "/Georgia-Okeeffe": [
        {
          "source": "/Georgia-Okeeffe",
          "target": "/notes/raw",
          "text": "notes/raw"
        },
        {
          "source": "/Georgia-Okeeffe",
          "target": "/notes/Art",
          "text": "notes/Art"
        },
        {
          "source": "/Georgia-Okeeffe",
          "target": "/American-Modernism",
          "text": "American Modernism"
        },
        {
          "source": "/Georgia-Okeeffe",
          "target": "/notes/frieda-kahlo",
          "text": "notes/frieda kahlo"
        },
        {
          "source": "/Georgia-Okeeffe",
          "target": "/womens-suffrage",
          "text": "women's suffrage"
        }
      ],
      "/Hieronymus-Bosch": [
        {
          "source": "/Hieronymus-Bosch",
          "target": "/notes/raw",
          "text": "notes/raw"
        }
      ],
      "/Home": [
        {
          "source": "/Home",
          "target": "/notes/Polly-Labs",
          "text": "notes/Polly Labs"
        },
        {
          "source": "/Home",
          "target": "/notes/FoodCo",
          "text": "notes/FoodCo"
        },
        {
          "source": "/Home",
          "target": "/notes/Repurposing-Technology",
          "text": "notes/Repurposing Technology"
        },
        {
          "source": "/Home",
          "target": "/notes/Joblio",
          "text": "notes/Joblio"
        },
        {
          "source": "/Home",
          "target": "/google",
          "text": "google"
        },
        {
          "source": "/Home",
          "target": "/notes/People",
          "text": "notes/People"
        },
        {
          "source": "/Home",
          "target": "/family",
          "text": "family"
        },
        {
          "source": "/Home",
          "target": "/relationship",
          "text": "relationship"
        },
        {
          "source": "/Home",
          "target": "/friends",
          "text": "friends"
        },
        {
          "source": "/Home",
          "target": "/notes/cooking",
          "text": "notes/cooking"
        },
        {
          "source": "/Home",
          "target": "/notes/Fitness",
          "text": "notes/Fitness"
        },
        {
          "source": "/Home",
          "target": "/music",
          "text": "music"
        },
        {
          "source": "/Home",
          "target": "/literature",
          "text": "literature"
        },
        {
          "source": "/Home",
          "target": "/film",
          "text": "film"
        },
        {
          "source": "/Home",
          "target": "/content",
          "text": "content"
        },
        {
          "source": "/Home",
          "target": "/notes/My-Obsidian-Methodology",
          "text": "notes/My Obsidian Methodology"
        },
        {
          "source": "/Home",
          "target": "/notes/roots",
          "text": "notes/roots"
        },
        {
          "source": "/Home",
          "target": "/moc",
          "text": "moc"
        }
      ],
      "/How-to-figure-out-how-Farmers-Sell": [
        {
          "source": "/How-to-figure-out-how-Farmers-Sell",
          "target": "/notes/raw",
          "text": "notes/raw"
        }
      ],
      "/Joblio": [
        {
          "source": "/Joblio",
          "target": "/notes/raw",
          "text": "notes/raw"
        }
      ],
      "/Local-Food-Marketplace": [
        {
          "source": "/Local-Food-Marketplace",
          "target": "/notes/raw",
          "text": "notes/raw"
        }
      ],
      "/Local-Orbit": [
        {
          "source": "/Local-Orbit",
          "target": "/notes/raw",
          "text": "notes/raw"
        }
      ],
      "/Nutrition": [
        {
          "source": "/Nutrition",
          "target": "/notes/raw",
          "text": "notes/raw"
        }
      ],
      "/People": [
        {
          "source": "/People",
          "target": "/notes/raw",
          "text": "notes/raw"
        },
        {
          "source": "/People",
          "target": "/aileen-wang",
          "text": "aileen wang"
        },
        {
          "source": "/People",
          "target": "/chiming-yang",
          "text": "chiming yang"
        },
        {
          "source": "/People",
          "target": "/kevin-yang",
          "text": "kevin yang"
        },
        {
          "source": "/People",
          "target": "/shuyuan-yang",
          "text": "shuyuan yang"
        },
        {
          "source": "/People",
          "target": "/jon-purizhansky",
          "text": "jon purizhansky"
        },
        {
          "source": "/People",
          "target": "/alina-shkolnikov",
          "text": "alina shkolnikov"
        },
        {
          "source": "/People",
          "target": "/cat-xu",
          "text": "cat xu"
        }
      ],
      "/Polly-Labs": [
        {
          "source": "/Polly-Labs",
          "target": "/notes/FoodCo",
          "text": "notes/FoodCo"
        },
        {
          "source": "/Polly-Labs",
          "target": "/notes/Repurposing-Technology",
          "text": "notes/Repurposing Technology"
        },
        {
          "source": "/Polly-Labs",
          "target": "/moc",
          "text": "moc"
        }
      ],
      "/Red-Tomato-Food-Hub": [
        {
          "source": "/Red-Tomato-Food-Hub",
          "target": "/notes/raw",
          "text": "notes/raw"
        }
      ],
      "/agriculture": [
        {
          "source": "/agriculture",
          "target": "/notes/raw",
          "text": "notes/raw"
        },
        {
          "source": "/agriculture",
          "target": "/notes/FoodCo",
          "text": "notes/FoodCo"
        }
      ],
      "/cooking": [
        {
          "source": "/cooking",
          "target": "/notes/raw",
          "text": "notes/raw"
        }
      ],
      "/frieda-kahlo": [
        {
          "source": "/frieda-kahlo",
          "target": "/notes/raw",
          "text": "notes/raw"
        },
        {
          "source": "/frieda-kahlo",
          "target": "/notes/Art",
          "text": "notes/Art"
        },
        {
          "source": "/frieda-kahlo",
          "target": "/Mexicayotl-Movement",
          "text": "Mexicayotl Movement"
        },
        {
          "source": "/frieda-kahlo",
          "target": "/notes/Hieronymus-Bosch",
          "text": "notes/Hieronymus Bosch"
        }
      ],
      "/notes/2023-08-17": [
        {
          "source": "/notes/2023-08-17",
          "target": "/notes/raw",
          "text": "notes/raw"
        }
      ],
      "/notes/2023-08-18": [
        {
          "source": "/notes/2023-08-18",
          "target": "/notes/raw",
          "text": "notes/raw"
        }
      ],
      "/notes/202308181153": [
        {
          "source": "/notes/202308181153",
          "target": "/notes/raw",
          "text": "notes/raw"
        }
      ],
      "/notes/Ambrook": [
        {
          "source": "/notes/Ambrook",
          "target": "/notes/raw",
          "text": "notes/raw"
        }
      ],
      "/notes/Bold-Salt-Lick": [
        {
          "source": "/notes/Bold-Salt-Lick",
          "target": "/notes/raw",
          "text": "notes/raw"
        }
      ],
      "/notes/CSA": [
        {
          "source": "/notes/CSA",
          "target": "/notes/raw",
          "text": "notes/raw"
        }
      ],
      "/notes/Climate-Risk-on-Supply-Chain": [
        {
          "source": "/notes/Climate-Risk-on-Supply-Chain",
          "target": "/notes/raw",
          "text": "notes/raw"
        }
      ],
      "/notes/Content-List": [
        {
          "source": "/notes/Content-List",
          "target": "/notes/raw",
          "text": "notes/raw"
        },
        {
          "source": "/notes/Content-List",
          "target": "/moc",
          "text": "moc"
        }
      ],
      "/notes/Conventional-vs-Controlled-Environment-Agriculture-Supply-Chains": [
        {
          "source": "/notes/Conventional-vs-Controlled-Environment-Agriculture-Supply-Chains",
          "target": "/notes/raw",
          "text": "notes/raw"
        },
        {
          "source": "/notes/Conventional-vs-Controlled-Environment-Agriculture-Supply-Chains",
          "target": "/notes/agriculture",
          "text": "notes/agriculture"
        }
      ],
      "/notes/Farmers-Market-Management": [
        {
          "source": "/notes/Farmers-Market-Management",
          "target": "/notes/raw",
          "text": "notes/raw"
        }
      ],
      "/notes/Fitness": [
        {
          "source": "/notes/Fitness",
          "target": "/notes/raw",
          "text": "notes/raw"
        },
        {
          "source": "/notes/Fitness",
          "target": "/https//www.hybridcalisthenics.com/programshttps//www.hybridcalisthenics.com/programs",
          "text": "hybrid calisthenics"
        }
      ],
      "/notes/Food-Hub": [
        {
          "source": "/notes/Food-Hub",
          "target": "/notes/raw",
          "text": "notes/raw"
        }
      ],
      "/notes/Food4All": [
        {
          "source": "/notes/Food4All",
          "target": "/notes/raw",
          "text": "notes/raw"
        }
      ],
      "/notes/FoodCo": [
        {
          "source": "/notes/FoodCo",
          "target": "/notes/Polly-Labs",
          "text": "notes/Polly Labs"
        },
        {
          "source": "/notes/FoodCo",
          "target": "/notes/FoodCo-Competitor-Analysis",
          "text": "notes/FoodCo Competitor Analysis"
        },
        {
          "source": "/notes/FoodCo",
          "target": "/notes/FoodCo-Distributor-Analysis",
          "text": "notes/FoodCo Distributor Analysis"
        },
        {
          "source": "/notes/FoodCo",
          "target": "/notes/FoodCo-Price-Analysis",
          "text": "notes/FoodCo Price Analysis"
        },
        {
          "source": "/notes/FoodCo",
          "target": "/notes/FoodCo-Farmer-Marketing-Analysis",
          "text": "notes/FoodCo Farmer Marketing Analysis"
        },
        {
          "source": "/notes/FoodCo",
          "target": "/notes/FoodCo-Customer-Analysis",
          "text": "notes/FoodCo Customer Analysis"
        },
        {
          "source": "/notes/FoodCo",
          "target": "/notes/CSA",
          "text": "notes/CSA"
        },
        {
          "source": "/notes/FoodCo",
          "target": "/moc",
          "text": "moc"
        }
      ],
      "/notes/FoodCo-Competitor-Analysis": [
        {
          "source": "/notes/FoodCo-Competitor-Analysis",
          "target": "/notes/Seven-Suns",
          "text": "notes/Seven Suns"
        },
        {
          "source": "/notes/FoodCo-Competitor-Analysis",
          "target": "/notes/Barn2Door",
          "text": "notes/Barn2Door"
        },
        {
          "source": "/notes/FoodCo-Competitor-Analysis",
          "target": "/notes/Bold-Salt-Lick",
          "text": "notes/Bold Salt Lick"
        },
        {
          "source": "/notes/FoodCo-Competitor-Analysis",
          "target": "/notes/Eat-From-Farms",
          "text": "notes/Eat From Farms"
        },
        {
          "source": "/notes/FoodCo-Competitor-Analysis",
          "target": "/notes/Food4All",
          "text": "notes/Food4All"
        },
        {
          "source": "/notes/FoodCo-Competitor-Analysis",
          "target": "/Meicai",
          "text": "Meicai"
        },
        {
          "source": "/notes/FoodCo-Competitor-Analysis",
          "target": "/notes/Local-Orbit",
          "text": "notes/Local Orbit"
        },
        {
          "source": "/notes/FoodCo-Competitor-Analysis",
          "target": "/notes/Ambrook",
          "text": "notes/Ambrook"
        },
        {
          "source": "/notes/FoodCo-Competitor-Analysis",
          "target": "/notes/Local-Food-Marketplace",
          "text": "notes/Local Food Marketplace"
        },
        {
          "source": "/notes/FoodCo-Competitor-Analysis",
          "target": "/notes/Foraged",
          "text": "notes/Foraged"
        }
      ],
      "/notes/FoodCo-Customer-Analysis": [
        {
          "source": "/notes/FoodCo-Customer-Analysis",
          "target": "/notes/raw",
          "text": "notes/raw"
        }
      ],
      "/notes/FoodCo-Distributor-Analysis": [
        {
          "source": "/notes/FoodCo-Distributor-Analysis",
          "target": "/notes/raw",
          "text": "notes/raw"
        },
        {
          "source": "/notes/FoodCo-Distributor-Analysis",
          "target": "/notes/Red-Tomato-Food-Hub",
          "text": "notes/Red Tomato Food Hub"
        },
        {
          "source": "/notes/FoodCo-Distributor-Analysis",
          "target": "/notes/Food-Hub",
          "text": "notes/Food Hub"
        },
        {
          "source": "/notes/FoodCo-Distributor-Analysis",
          "target": "/notes/Red-Tomato-Food-Hub",
          "text": "notes/Red Tomato Food Hub"
        }
      ],
      "/notes/FoodCo-Farmer-Marketing-Analysis": [
        {
          "source": "/notes/FoodCo-Farmer-Marketing-Analysis",
          "target": "/notes/raw",
          "text": "notes/raw"
        }
      ],
      "/notes/FoodCo-Price-Analysis": [
        {
          "source": "/notes/FoodCo-Price-Analysis",
          "target": "/notes/raw",
          "text": "notes/raw"
        }
      ],
      "/notes/Foraged": [
        {
          "source": "/notes/Foraged",
          "target": "/notes/raw",
          "text": "notes/raw"
        }
      ],
      "/notes/Georgia-Okeeffe": [
        {
          "source": "/notes/Georgia-Okeeffe",
          "target": "/notes/raw",
          "text": "notes/raw"
        },
        {
          "source": "/notes/Georgia-Okeeffe",
          "target": "/notes/Art",
          "text": "notes/Art"
        },
        {
          "source": "/notes/Georgia-Okeeffe",
          "target": "/American-Modernism",
          "text": "American Modernism"
        },
        {
          "source": "/notes/Georgia-Okeeffe",
          "target": "/notes/frieda-kahlo",
          "text": "notes/frieda kahlo"
        },
        {
          "source": "/notes/Georgia-Okeeffe",
          "target": "/womens-suffrage",
          "text": "women's suffrage"
        }
      ],
      "/notes/Hieronymus-Bosch": [
        {
          "source": "/notes/Hieronymus-Bosch",
          "target": "/notes/raw",
          "text": "notes/raw"
        }
      ],
      "/notes/How-to-figure-out-how-Farmers-Sell": [
        {
          "source": "/notes/How-to-figure-out-how-Farmers-Sell",
          "target": "/notes/raw",
          "text": "notes/raw"
        }
      ],
      "/notes/Joblio": [
        {
          "source": "/notes/Joblio",
          "target": "/notes/raw",
          "text": "notes/raw"
        }
      ],
      "/notes/Local-Food-Marketplace": [
        {
          "source": "/notes/Local-Food-Marketplace",
          "target": "/notes/raw",
          "text": "notes/raw"
        }
      ],
      "/notes/Local-Orbit": [
        {
          "source": "/notes/Local-Orbit",
          "target": "/notes/raw",
          "text": "notes/raw"
        }
      ],
      "/notes/Nutrition": [
        {
          "source": "/notes/Nutrition",
          "target": "/notes/raw",
          "text": "notes/raw"
        }
      ],
      "/notes/People": [
        {
          "source": "/notes/People",
          "target": "/notes/raw",
          "text": "notes/raw"
        },
        {
          "source": "/notes/People",
          "target": "/aileen-wang",
          "text": "aileen wang"
        },
        {
          "source": "/notes/People",
          "target": "/chiming-yang",
          "text": "chiming yang"
        },
        {
          "source": "/notes/People",
          "target": "/kevin-yang",
          "text": "kevin yang"
        },
        {
          "source": "/notes/People",
          "target": "/shuyuan-yang",
          "text": "shuyuan yang"
        },
        {
          "source": "/notes/People",
          "target": "/jon-purizhansky",
          "text": "jon purizhansky"
        },
        {
          "source": "/notes/People",
          "target": "/alina-shkolnikov",
          "text": "alina shkolnikov"
        },
        {
          "source": "/notes/People",
          "target": "/cat-xu",
          "text": "cat xu"
        }
      ],
      "/notes/Polly-Labs": [
        {
          "source": "/notes/Polly-Labs",
          "target": "/notes/FoodCo",
          "text": "notes/FoodCo"
        },
        {
          "source": "/notes/Polly-Labs",
          "target": "/notes/Repurposing-Technology",
          "text": "notes/Repurposing Technology"
        },
        {
          "source": "/notes/Polly-Labs",
          "target": "/moc",
          "text": "moc"
        }
      ],
      "/notes/Red-Tomato-Food-Hub": [
        {
          "source": "/notes/Red-Tomato-Food-Hub",
          "target": "/notes/raw",
          "text": "notes/raw"
        }
      ],
      "/notes/agriculture": [
        {
          "source": "/notes/agriculture",
          "target": "/notes/raw",
          "text": "notes/raw"
        },
        {
          "source": "/notes/agriculture",
          "target": "/notes/FoodCo",
          "text": "notes/FoodCo"
        }
      ],
      "/notes/cooking": [
        {
          "source": "/notes/cooking",
          "target": "/notes/raw",
          "text": "notes/raw"
        }
      ],
      "/notes/frieda-kahlo": [
        {
          "source": "/notes/frieda-kahlo",
          "target": "/notes/raw",
          "text": "notes/raw"
        },
        {
          "source": "/notes/frieda-kahlo",
          "target": "/notes/Art",
          "text": "notes/Art"
        },
        {
          "source": "/notes/frieda-kahlo",
          "target": "/Mexicayotl-Movement",
          "text": "Mexicayotl Movement"
        },
        {
          "source": "/notes/frieda-kahlo",
          "target": "/notes/Hieronymus-Bosch",
          "text": "notes/Hieronymus Bosch"
        }
      ],
      "/notes/raw": [
        {
          "source": "/notes/raw",
          "target": "/notes/raw",
          "text": "notes/raw"
        }
      ],
      "/notes/roots": [
        {
          "source": "/notes/roots",
          "target": "/notes/raw",
          "text": "notes/raw"
        },
        {
          "source": "/notes/roots",
          "target": "/notes/agriculture",
          "text": "notes/agriculture"
        }
      ],
      "/raw": [
        {
          "source": "/raw",
          "target": "/notes/raw",
          "text": "notes/raw"
        }
      ],
      "/roots": [
        {
          "source": "/roots",
          "target": "/notes/raw",
          "text": "notes/raw"
        },
        {
          "source": "/roots",
          "target": "/notes/agriculture",
          "text": "notes/agriculture"
        }
      ]
    },
    "backlinks": {
      "/American-Modernism": [
        {
          "source": "/Georgia-Okeeffe",
          "target": "/American-Modernism",
          "text": "American Modernism"
        },
        {
          "source": "/notes/Georgia-Okeeffe",
          "target": "/American-Modernism",
          "text": "American Modernism"
        }
      ],
      "/Meicai": [
        {
          "source": "/FoodCo-Competitor-Analysis",
          "target": "/Meicai",
          "text": "Meicai"
        },
        {
          "source": "/notes/FoodCo-Competitor-Analysis",
          "target": "/Meicai",
          "text": "Meicai"
        }
      ],
      "/Mexicayotl-Movement": [
        {
          "source": "/frieda-kahlo",
          "target": "/Mexicayotl-Movement",
          "text": "Mexicayotl Movement"
        },
        {
          "source": "/notes/frieda-kahlo",
          "target": "/Mexicayotl-Movement",
          "text": "Mexicayotl Movement"
        }
      ],
      "/aileen-wang": [
        {
          "source": "/People",
          "target": "/aileen-wang",
          "text": "aileen wang"
        },
        {
          "source": "/notes/People",
          "target": "/aileen-wang",
          "text": "aileen wang"
        }
      ],
      "/alina-shkolnikov": [
        {
          "source": "/People",
          "target": "/alina-shkolnikov",
          "text": "alina shkolnikov"
        },
        {
          "source": "/notes/People",
          "target": "/alina-shkolnikov",
          "text": "alina shkolnikov"
        }
      ],
      "/cat-xu": [
        {
          "source": "/People",
          "target": "/cat-xu",
          "text": "cat xu"
        },
        {
          "source": "/notes/People",
          "target": "/cat-xu",
          "text": "cat xu"
        }
      ],
      "/chiming-yang": [
        {
          "source": "/People",
          "target": "/chiming-yang",
          "text": "chiming yang"
        },
        {
          "source": "/notes/People",
          "target": "/chiming-yang",
          "text": "chiming yang"
        }
      ],
      "/content": [
        {
          "source": "/Home",
          "target": "/content",
          "text": "content"
        },
        {
          "source": "/",
          "target": "/content",
          "text": "content"
        }
      ],
      "/family": [
        {
          "source": "/Home",
          "target": "/family",
          "text": "family"
        },
        {
          "source": "/",
          "target": "/family",
          "text": "family"
        }
      ],
      "/film": [
        {
          "source": "/Home",
          "target": "/film",
          "text": "film"
        },
        {
          "source": "/",
          "target": "/film",
          "text": "film"
        }
      ],
      "/friends": [
        {
          "source": "/Home",
          "target": "/friends",
          "text": "friends"
        },
        {
          "source": "/",
          "target": "/friends",
          "text": "friends"
        }
      ],
      "/google": [
        {
          "source": "/Home",
          "target": "/google",
          "text": "google"
        },
        {
          "source": "/",
          "target": "/google",
          "text": "google"
        }
      ],
      "/https//www.hybridcalisthenics.com/programshttps//www.hybridcalisthenics.com/programs": [
        {
          "source": "/Fitness",
          "target": "/https//www.hybridcalisthenics.com/programshttps//www.hybridcalisthenics.com/programs",
          "text": "hybrid calisthenics"
        },
        {
          "source": "/notes/Fitness",
          "target": "/https//www.hybridcalisthenics.com/programshttps//www.hybridcalisthenics.com/programs",
          "text": "hybrid calisthenics"
        }
      ],
      "/jon-purizhansky": [
        {
          "source": "/People",
          "target": "/jon-purizhansky",
          "text": "jon purizhansky"
        },
        {
          "source": "/notes/People",
          "target": "/jon-purizhansky",
          "text": "jon purizhansky"
        }
      ],
      "/kevin-yang": [
        {
          "source": "/People",
          "target": "/kevin-yang",
          "text": "kevin yang"
        },
        {
          "source": "/notes/People",
          "target": "/kevin-yang",
          "text": "kevin yang"
        }
      ],
      "/literature": [
        {
          "source": "/Home",
          "target": "/literature",
          "text": "literature"
        },
        {
          "source": "/",
          "target": "/literature",
          "text": "literature"
        }
      ],
      "/moc": [
        {
          "source": "/Content-List",
          "target": "/moc",
          "text": "moc"
        },
        {
          "source": "/FoodCo",
          "target": "/moc",
          "text": "moc"
        },
        {
          "source": "/Home",
          "target": "/moc",
          "text": "moc"
        },
        {
          "source": "/Polly-Labs",
          "target": "/moc",
          "text": "moc"
        },
        {
          "source": "/",
          "target": "/moc",
          "text": "moc"
        },
        {
          "source": "/notes/Content-List",
          "target": "/moc",
          "text": "moc"
        },
        {
          "source": "/notes/FoodCo",
          "target": "/moc",
          "text": "moc"
        },
        {
          "source": "/notes/Polly-Labs",
          "target": "/moc",
          "text": "moc"
        }
      ],
      "/music": [
        {
          "source": "/Home",
          "target": "/music",
          "text": "music"
        },
        {
          "source": "/",
          "target": "/music",
          "text": "music"
        }
      ],
      "/notes/Ambrook": [
        {
          "source": "/FoodCo-Competitor-Analysis",
          "target": "/notes/Ambrook",
          "text": "notes/Ambrook"
        },
        {
          "source": "/notes/FoodCo-Competitor-Analysis",
          "target": "/notes/Ambrook",
          "text": "notes/Ambrook"
        }
      ],
      "/notes/Art": [
        {
          "source": "/Georgia-Okeeffe",
          "target": "/notes/Art",
          "text": "notes/Art"
        },
        {
          "source": "/frieda-kahlo",
          "target": "/notes/Art",
          "text": "notes/Art"
        },
        {
          "source": "/notes/Georgia-Okeeffe",
          "target": "/notes/Art",
          "text": "notes/Art"
        },
        {
          "source": "/notes/frieda-kahlo",
          "target": "/notes/Art",
          "text": "notes/Art"
        }
      ],
      "/notes/Barn2Door": [
        {
          "source": "/FoodCo-Competitor-Analysis",
          "target": "/notes/Barn2Door",
          "text": "notes/Barn2Door"
        },
        {
          "source": "/notes/FoodCo-Competitor-Analysis",
          "target": "/notes/Barn2Door",
          "text": "notes/Barn2Door"
        }
      ],
      "/notes/Bold-Salt-Lick": [
        {
          "source": "/FoodCo-Competitor-Analysis",
          "target": "/notes/Bold-Salt-Lick",
          "text": "notes/Bold Salt Lick"
        },
        {
          "source": "/notes/FoodCo-Competitor-Analysis",
          "target": "/notes/Bold-Salt-Lick",
          "text": "notes/Bold Salt Lick"
        }
      ],
      "/notes/CSA": [
        {
          "source": "/FoodCo",
          "target": "/notes/CSA",
          "text": "notes/CSA"
        },
        {
          "source": "/notes/FoodCo",
          "target": "/notes/CSA",
          "text": "notes/CSA"
        }
      ],
      "/notes/Eat-From-Farms": [
        {
          "source": "/FoodCo-Competitor-Analysis",
          "target": "/notes/Eat-From-Farms",
          "text": "notes/Eat From Farms"
        },
        {
          "source": "/notes/FoodCo-Competitor-Analysis",
          "target": "/notes/Eat-From-Farms",
          "text": "notes/Eat From Farms"
        }
      ],
      "/notes/Fitness": [
        {
          "source": "/Home",
          "target": "/notes/Fitness",
          "text": "notes/Fitness"
        },
        {
          "source": "/",
          "target": "/notes/Fitness",
          "text": "notes/Fitness"
        }
      ],
      "/notes/Food-Hub": [
        {
          "source": "/FoodCo-Distributor-Analysis",
          "target": "/notes/Food-Hub",
          "text": "notes/Food Hub"
        },
        {
          "source": "/notes/FoodCo-Distributor-Analysis",
          "target": "/notes/Food-Hub",
          "text": "notes/Food Hub"
        }
      ],
      "/notes/Food4All": [
        {
          "source": "/FoodCo-Competitor-Analysis",
          "target": "/notes/Food4All",
          "text": "notes/Food4All"
        },
        {
          "source": "/notes/FoodCo-Competitor-Analysis",
          "target": "/notes/Food4All",
          "text": "notes/Food4All"
        }
      ],
      "/notes/FoodCo": [
        {
          "source": "/Home",
          "target": "/notes/FoodCo",
          "text": "notes/FoodCo"
        },
        {
          "source": "/Polly-Labs",
          "target": "/notes/FoodCo",
          "text": "notes/FoodCo"
        },
        {
          "source": "/",
          "target": "/notes/FoodCo",
          "text": "notes/FoodCo"
        },
        {
          "source": "/agriculture",
          "target": "/notes/FoodCo",
          "text": "notes/FoodCo"
        },
        {
          "source": "/notes/Polly-Labs",
          "target": "/notes/FoodCo",
          "text": "notes/FoodCo"
        },
        {
          "source": "/notes/agriculture",
          "target": "/notes/FoodCo",
          "text": "notes/FoodCo"
        }
      ],
      "/notes/FoodCo-Competitor-Analysis": [
        {
          "source": "/FoodCo",
          "target": "/notes/FoodCo-Competitor-Analysis",
          "text": "notes/FoodCo Competitor Analysis"
        },
        {
          "source": "/notes/FoodCo",
          "target": "/notes/FoodCo-Competitor-Analysis",
          "text": "notes/FoodCo Competitor Analysis"
        }
      ],
      "/notes/FoodCo-Customer-Analysis": [
        {
          "source": "/FoodCo",
          "target": "/notes/FoodCo-Customer-Analysis",
          "text": "notes/FoodCo Customer Analysis"
        },
        {
          "source": "/notes/FoodCo",
          "target": "/notes/FoodCo-Customer-Analysis",
          "text": "notes/FoodCo Customer Analysis"
        }
      ],
      "/notes/FoodCo-Distributor-Analysis": [
        {
          "source": "/FoodCo",
          "target": "/notes/FoodCo-Distributor-Analysis",
          "text": "notes/FoodCo Distributor Analysis"
        },
        {
          "source": "/notes/FoodCo",
          "target": "/notes/FoodCo-Distributor-Analysis",
          "text": "notes/FoodCo Distributor Analysis"
        }
      ],
      "/notes/FoodCo-Farmer-Marketing-Analysis": [
        {
          "source": "/FoodCo",
          "target": "/notes/FoodCo-Farmer-Marketing-Analysis",
          "text": "notes/FoodCo Farmer Marketing Analysis"
        },
        {
          "source": "/notes/FoodCo",
          "target": "/notes/FoodCo-Farmer-Marketing-Analysis",
          "text": "notes/FoodCo Farmer Marketing Analysis"
        }
      ],
      "/notes/FoodCo-Price-Analysis": [
        {
          "source": "/FoodCo",
          "target": "/notes/FoodCo-Price-Analysis",
          "text": "notes/FoodCo Price Analysis"
        },
        {
          "source": "/notes/FoodCo",
          "target": "/notes/FoodCo-Price-Analysis",
          "text": "notes/FoodCo Price Analysis"
        }
      ],
      "/notes/Foraged": [
        {
          "source": "/FoodCo-Competitor-Analysis",
          "target": "/notes/Foraged",
          "text": "notes/Foraged"
        },
        {
          "source": "/notes/FoodCo-Competitor-Analysis",
          "target": "/notes/Foraged",
          "text": "notes/Foraged"
        }
      ],
      "/notes/Hieronymus-Bosch": [
        {
          "source": "/frieda-kahlo",
          "target": "/notes/Hieronymus-Bosch",
          "text": "notes/Hieronymus Bosch"
        },
        {
          "source": "/notes/frieda-kahlo",
          "target": "/notes/Hieronymus-Bosch",
          "text": "notes/Hieronymus Bosch"
        }
      ],
      "/notes/Joblio": [
        {
          "source": "/Home",
          "target": "/notes/Joblio",
          "text": "notes/Joblio"
        },
        {
          "source": "/",
          "target": "/notes/Joblio",
          "text": "notes/Joblio"
        }
      ],
      "/notes/Local-Food-Marketplace": [
        {
          "source": "/FoodCo-Competitor-Analysis",
          "target": "/notes/Local-Food-Marketplace",
          "text": "notes/Local Food Marketplace"
        },
        {
          "source": "/notes/FoodCo-Competitor-Analysis",
          "target": "/notes/Local-Food-Marketplace",
          "text": "notes/Local Food Marketplace"
        }
      ],
      "/notes/Local-Orbit": [
        {
          "source": "/FoodCo-Competitor-Analysis",
          "target": "/notes/Local-Orbit",
          "text": "notes/Local Orbit"
        },
        {
          "source": "/notes/FoodCo-Competitor-Analysis",
          "target": "/notes/Local-Orbit",
          "text": "notes/Local Orbit"
        }
      ],
      "/notes/My-Obsidian-Methodology": [
        {
          "source": "/Home",
          "target": "/notes/My-Obsidian-Methodology",
          "text": "notes/My Obsidian Methodology"
        },
        {
          "source": "/",
          "target": "/notes/My-Obsidian-Methodology",
          "text": "notes/My Obsidian Methodology"
        }
      ],
      "/notes/People": [
        {
          "source": "/Home",
          "target": "/notes/People",
          "text": "notes/People"
        },
        {
          "source": "/",
          "target": "/notes/People",
          "text": "notes/People"
        }
      ],
      "/notes/Polly-Labs": [
        {
          "source": "/FoodCo",
          "target": "/notes/Polly-Labs",
          "text": "notes/Polly Labs"
        },
        {
          "source": "/Home",
          "target": "/notes/Polly-Labs",
          "text": "notes/Polly Labs"
        },
        {
          "source": "/",
          "target": "/notes/Polly-Labs",
          "text": "notes/Polly Labs"
        },
        {
          "source": "/notes/FoodCo",
          "target": "/notes/Polly-Labs",
          "text": "notes/Polly Labs"
        }
      ],
      "/notes/Red-Tomato-Food-Hub": [
        {
          "source": "/FoodCo-Distributor-Analysis",
          "target": "/notes/Red-Tomato-Food-Hub",
          "text": "notes/Red Tomato Food Hub"
        },
        {
          "source": "/FoodCo-Distributor-Analysis",
          "target": "/notes/Red-Tomato-Food-Hub",
          "text": "notes/Red Tomato Food Hub"
        },
        {
          "source": "/notes/FoodCo-Distributor-Analysis",
          "target": "/notes/Red-Tomato-Food-Hub",
          "text": "notes/Red Tomato Food Hub"
        },
        {
          "source": "/notes/FoodCo-Distributor-Analysis",
          "target": "/notes/Red-Tomato-Food-Hub",
          "text": "notes/Red Tomato Food Hub"
        }
      ],
      "/notes/Repurposing-Technology": [
        {
          "source": "/Home",
          "target": "/notes/Repurposing-Technology",
          "text": "notes/Repurposing Technology"
        },
        {
          "source": "/Polly-Labs",
          "target": "/notes/Repurposing-Technology",
          "text": "notes/Repurposing Technology"
        },
        {
          "source": "/",
          "target": "/notes/Repurposing-Technology",
          "text": "notes/Repurposing Technology"
        },
        {
          "source": "/notes/Polly-Labs",
          "target": "/notes/Repurposing-Technology",
          "text": "notes/Repurposing Technology"
        }
      ],
      "/notes/Seven-Suns": [
        {
          "source": "/FoodCo-Competitor-Analysis",
          "target": "/notes/Seven-Suns",
          "text": "notes/Seven Suns"
        },
        {
          "source": "/notes/FoodCo-Competitor-Analysis",
          "target": "/notes/Seven-Suns",
          "text": "notes/Seven Suns"
        }
      ],
      "/notes/agriculture": [
        {
          "source": "/Conventional-vs-Controlled-Environment-Agriculture-Supply-Chains",
          "target": "/notes/agriculture",
          "text": "notes/agriculture"
        },
        {
          "source": "/notes/Conventional-vs-Controlled-Environment-Agriculture-Supply-Chains",
          "target": "/notes/agriculture",
          "text": "notes/agriculture"
        },
        {
          "source": "/notes/roots",
          "target": "/notes/agriculture",
          "text": "notes/agriculture"
        },
        {
          "source": "/roots",
          "target": "/notes/agriculture",
          "text": "notes/agriculture"
        }
      ],
      "/notes/cooking": [
        {
          "source": "/Home",
          "target": "/notes/cooking",
          "text": "notes/cooking"
        },
        {
          "source": "/",
          "target": "/notes/cooking",
          "text": "notes/cooking"
        }
      ],
      "/notes/frieda-kahlo": [
        {
          "source": "/Georgia-Okeeffe",
          "target": "/notes/frieda-kahlo",
          "text": "notes/frieda kahlo"
        },
        {
          "source": "/notes/Georgia-Okeeffe",
          "target": "/notes/frieda-kahlo",
          "text": "notes/frieda kahlo"
        }
      ],
      "/notes/raw": [
        {
          "source": "/2023-08-17",
          "target": "/notes/raw",
          "text": "notes/raw"
        },
        {
          "source": "/2023-08-18",
          "target": "/notes/raw",
          "text": "notes/raw"
        },
        {
          "source": "/202308181153",
          "target": "/notes/raw",
          "text": "notes/raw"
        },
        {
          "source": "/Ambrook",
          "target": "/notes/raw",
          "text": "notes/raw"
        },
        {
          "source": "/Bold-Salt-Lick",
          "target": "/notes/raw",
          "text": "notes/raw"
        },
        {
          "source": "/CSA",
          "target": "/notes/raw",
          "text": "notes/raw"
        },
        {
          "source": "/Climate-Risk-on-Supply-Chain",
          "target": "/notes/raw",
          "text": "notes/raw"
        },
        {
          "source": "/Content-List",
          "target": "/notes/raw",
          "text": "notes/raw"
        },
        {
          "source": "/Conventional-vs-Controlled-Environment-Agriculture-Supply-Chains",
          "target": "/notes/raw",
          "text": "notes/raw"
        },
        {
          "source": "/Farmers-Market-Management",
          "target": "/notes/raw",
          "text": "notes/raw"
        },
        {
          "source": "/Fitness",
          "target": "/notes/raw",
          "text": "notes/raw"
        },
        {
          "source": "/Food-Hub",
          "target": "/notes/raw",
          "text": "notes/raw"
        },
        {
          "source": "/Food4All",
          "target": "/notes/raw",
          "text": "notes/raw"
        },
        {
          "source": "/FoodCo-Customer-Analysis",
          "target": "/notes/raw",
          "text": "notes/raw"
        },
        {
          "source": "/FoodCo-Distributor-Analysis",
          "target": "/notes/raw",
          "text": "notes/raw"
        },
        {
          "source": "/FoodCo-Farmer-Marketing-Analysis",
          "target": "/notes/raw",
          "text": "notes/raw"
        },
        {
          "source": "/FoodCo-Price-Analysis",
          "target": "/notes/raw",
          "text": "notes/raw"
        },
        {
          "source": "/Foraged",
          "target": "/notes/raw",
          "text": "notes/raw"
        },
        {
          "source": "/Georgia-Okeeffe",
          "target": "/notes/raw",
          "text": "notes/raw"
        },
        {
          "source": "/Hieronymus-Bosch",
          "target": "/notes/raw",
          "text": "notes/raw"
        },
        {
          "source": "/How-to-figure-out-how-Farmers-Sell",
          "target": "/notes/raw",
          "text": "notes/raw"
        },
        {
          "source": "/Joblio",
          "target": "/notes/raw",
          "text": "notes/raw"
        },
        {
          "source": "/Local-Food-Marketplace",
          "target": "/notes/raw",
          "text": "notes/raw"
        },
        {
          "source": "/Local-Orbit",
          "target": "/notes/raw",
          "text": "notes/raw"
        },
        {
          "source": "/Nutrition",
          "target": "/notes/raw",
          "text": "notes/raw"
        },
        {
          "source": "/People",
          "target": "/notes/raw",
          "text": "notes/raw"
        },
        {
          "source": "/Red-Tomato-Food-Hub",
          "target": "/notes/raw",
          "text": "notes/raw"
        },
        {
          "source": "/agriculture",
          "target": "/notes/raw",
          "text": "notes/raw"
        },
        {
          "source": "/cooking",
          "target": "/notes/raw",
          "text": "notes/raw"
        },
        {
          "source": "/frieda-kahlo",
          "target": "/notes/raw",
          "text": "notes/raw"
        },
        {
          "source": "/notes/2023-08-17",
          "target": "/notes/raw",
          "text": "notes/raw"
        },
        {
          "source": "/notes/2023-08-18",
          "target": "/notes/raw",
          "text": "notes/raw"
        },
        {
          "source": "/notes/202308181153",
          "target": "/notes/raw",
          "text": "notes/raw"
        },
        {
          "source": "/notes/Ambrook",
          "target": "/notes/raw",
          "text": "notes/raw"
        },
        {
          "source": "/notes/Bold-Salt-Lick",
          "target": "/notes/raw",
          "text": "notes/raw"
        },
        {
          "source": "/notes/CSA",
          "target": "/notes/raw",
          "text": "notes/raw"
        },
        {
          "source": "/notes/Climate-Risk-on-Supply-Chain",
          "target": "/notes/raw",
          "text": "notes/raw"
        },
        {
          "source": "/notes/Content-List",
          "target": "/notes/raw",
          "text": "notes/raw"
        },
        {
          "source": "/notes/Conventional-vs-Controlled-Environment-Agriculture-Supply-Chains",
          "target": "/notes/raw",
          "text": "notes/raw"
        },
        {
          "source": "/notes/Farmers-Market-Management",
          "target": "/notes/raw",
          "text": "notes/raw"
        },
        {
          "source": "/notes/Fitness",
          "target": "/notes/raw",
          "text": "notes/raw"
        },
        {
          "source": "/notes/Food-Hub",
          "target": "/notes/raw",
          "text": "notes/raw"
        },
        {
          "source": "/notes/Food4All",
          "target": "/notes/raw",
          "text": "notes/raw"
        },
        {
          "source": "/notes/FoodCo-Customer-Analysis",
          "target": "/notes/raw",
          "text": "notes/raw"
        },
        {
          "source": "/notes/FoodCo-Distributor-Analysis",
          "target": "/notes/raw",
          "text": "notes/raw"
        },
        {
          "source": "/notes/FoodCo-Farmer-Marketing-Analysis",
          "target": "/notes/raw",
          "text": "notes/raw"
        },
        {
          "source": "/notes/FoodCo-Price-Analysis",
          "target": "/notes/raw",
          "text": "notes/raw"
        },
        {
          "source": "/notes/Foraged",
          "target": "/notes/raw",
          "text": "notes/raw"
        },
        {
          "source": "/notes/Georgia-Okeeffe",
          "target": "/notes/raw",
          "text": "notes/raw"
        },
        {
          "source": "/notes/Hieronymus-Bosch",
          "target": "/notes/raw",
          "text": "notes/raw"
        },
        {
          "source": "/notes/How-to-figure-out-how-Farmers-Sell",
          "target": "/notes/raw",
          "text": "notes/raw"
        },
        {
          "source": "/notes/Joblio",
          "target": "/notes/raw",
          "text": "notes/raw"
        },
        {
          "source": "/notes/Local-Food-Marketplace",
          "target": "/notes/raw",
          "text": "notes/raw"
        },
        {
          "source": "/notes/Local-Orbit",
          "target": "/notes/raw",
          "text": "notes/raw"
        },
        {
          "source": "/notes/Nutrition",
          "target": "/notes/raw",
          "text": "notes/raw"
        },
        {
          "source": "/notes/People",
          "target": "/notes/raw",
          "text": "notes/raw"
        },
        {
          "source": "/notes/Red-Tomato-Food-Hub",
          "target": "/notes/raw",
          "text": "notes/raw"
        },
        {
          "source": "/notes/agriculture",
          "target": "/notes/raw",
          "text": "notes/raw"
        },
        {
          "source": "/notes/cooking",
          "target": "/notes/raw",
          "text": "notes/raw"
        },
        {
          "source": "/notes/frieda-kahlo",
          "target": "/notes/raw",
          "text": "notes/raw"
        },
        {
          "source": "/notes/raw",
          "target": "/notes/raw",
          "text": "notes/raw"
        },
        {
          "source": "/notes/roots",
          "target": "/notes/raw",
          "text": "notes/raw"
        },
        {
          "source": "/raw",
          "target": "/notes/raw",
          "text": "notes/raw"
        },
        {
          "source": "/roots",
          "target": "/notes/raw",
          "text": "notes/raw"
        }
      ],
      "/notes/roots": [
        {
          "source": "/Home",
          "target": "/notes/roots",
          "text": "notes/roots"
        },
        {
          "source": "/",
          "target": "/notes/roots",
          "text": "notes/roots"
        }
      ],
      "/relationship": [
        {
          "source": "/Home",
          "target": "/relationship",
          "text": "relationship"
        },
        {
          "source": "/",
          "target": "/relationship",
          "text": "relationship"
        }
      ],
      "/shuyuan-yang": [
        {
          "source": "/People",
          "target": "/shuyuan-yang",
          "text": "shuyuan yang"
        },
        {
          "source": "/notes/People",
          "target": "/shuyuan-yang",
          "text": "shuyuan yang"
        }
      ],
      "/womens-suffrage": [
        {
          "source": "/Georgia-Okeeffe",
          "target": "/womens-suffrage",
          "text": "women's suffrage"
        },
        {
          "source": "/notes/Georgia-Okeeffe",
          "target": "/womens-suffrage",
          "text": "women's suffrage"
        }
      ]
    }
  },
  "links": [
    {
      "source": "/2023-08-17",
      "target": "/notes/raw",
      "text": "notes/raw"
    },
    {
      "source": "/2023-08-18",
      "target": "/notes/raw",
      "text": "notes/raw"
    },
    {
      "source": "/202308181153",
      "target": "/notes/raw",
      "text": "notes/raw"
    },
    {
      "source": "/Ambrook",
      "target": "/notes/raw",
      "text": "notes/raw"
    },
    {
      "source": "/Bold-Salt-Lick",
      "target": "/notes/raw",
      "text": "notes/raw"
    },
    {
      "source": "/CSA",
      "target": "/notes/raw",
      "text": "notes/raw"
    },
    {
      "source": "/Climate-Risk-on-Supply-Chain",
      "target": "/notes/raw",
      "text": "notes/raw"
    },
    {
      "source": "/Content-List",
      "target": "/notes/raw",
      "text": "notes/raw"
    },
    {
      "source": "/Content-List",
      "target": "/moc",
      "text": "moc"
    },
    {
      "source": "/Conventional-vs-Controlled-Environment-Agriculture-Supply-Chains",
      "target": "/notes/raw",
      "text": "notes/raw"
    },
    {
      "source": "/Conventional-vs-Controlled-Environment-Agriculture-Supply-Chains",
      "target": "/notes/agriculture",
      "text": "notes/agriculture"
    },
    {
      "source": "/Farmers-Market-Management",
      "target": "/notes/raw",
      "text": "notes/raw"
    },
    {
      "source": "/Fitness",
      "target": "/notes/raw",
      "text": "notes/raw"
    },
    {
      "source": "/Fitness",
      "target": "/https//www.hybridcalisthenics.com/programshttps//www.hybridcalisthenics.com/programs",
      "text": "hybrid calisthenics"
    },
    {
      "source": "/Food-Hub",
      "target": "/notes/raw",
      "text": "notes/raw"
    },
    {
      "source": "/Food4All",
      "target": "/notes/raw",
      "text": "notes/raw"
    },
    {
      "source": "/FoodCo-Competitor-Analysis",
      "target": "/notes/Seven-Suns",
      "text": "notes/Seven Suns"
    },
    {
      "source": "/FoodCo-Competitor-Analysis",
      "target": "/notes/Barn2Door",
      "text": "notes/Barn2Door"
    },
    {
      "source": "/FoodCo-Competitor-Analysis",
      "target": "/notes/Bold-Salt-Lick",
      "text": "notes/Bold Salt Lick"
    },
    {
      "source": "/FoodCo-Competitor-Analysis",
      "target": "/notes/Eat-From-Farms",
      "text": "notes/Eat From Farms"
    },
    {
      "source": "/FoodCo-Competitor-Analysis",
      "target": "/notes/Food4All",
      "text": "notes/Food4All"
    },
    {
      "source": "/FoodCo-Competitor-Analysis",
      "target": "/Meicai",
      "text": "Meicai"
    },
    {
      "source": "/FoodCo-Competitor-Analysis",
      "target": "/notes/Local-Orbit",
      "text": "notes/Local Orbit"
    },
    {
      "source": "/FoodCo-Competitor-Analysis",
      "target": "/notes/Ambrook",
      "text": "notes/Ambrook"
    },
    {
      "source": "/FoodCo-Competitor-Analysis",
      "target": "/notes/Local-Food-Marketplace",
      "text": "notes/Local Food Marketplace"
    },
    {
      "source": "/FoodCo-Competitor-Analysis",
      "target": "/notes/Foraged",
      "text": "notes/Foraged"
    },
    {
      "source": "/FoodCo-Customer-Analysis",
      "target": "/notes/raw",
      "text": "notes/raw"
    },
    {
      "source": "/FoodCo-Distributor-Analysis",
      "target": "/notes/raw",
      "text": "notes/raw"
    },
    {
      "source": "/FoodCo-Distributor-Analysis",
      "target": "/notes/Red-Tomato-Food-Hub",
      "text": "notes/Red Tomato Food Hub"
    },
    {
      "source": "/FoodCo-Distributor-Analysis",
      "target": "/notes/Food-Hub",
      "text": "notes/Food Hub"
    },
    {
      "source": "/FoodCo-Distributor-Analysis",
      "target": "/notes/Red-Tomato-Food-Hub",
      "text": "notes/Red Tomato Food Hub"
    },
    {
      "source": "/FoodCo-Farmer-Marketing-Analysis",
      "target": "/notes/raw",
      "text": "notes/raw"
    },
    {
      "source": "/FoodCo-Price-Analysis",
      "target": "/notes/raw",
      "text": "notes/raw"
    },
    {
      "source": "/FoodCo",
      "target": "/notes/Polly-Labs",
      "text": "notes/Polly Labs"
    },
    {
      "source": "/FoodCo",
      "target": "/notes/FoodCo-Competitor-Analysis",
      "text": "notes/FoodCo Competitor Analysis"
    },
    {
      "source": "/FoodCo",
      "target": "/notes/FoodCo-Distributor-Analysis",
      "text": "notes/FoodCo Distributor Analysis"
    },
    {
      "source": "/FoodCo",
      "target": "/notes/FoodCo-Price-Analysis",
      "text": "notes/FoodCo Price Analysis"
    },
    {
      "source": "/FoodCo",
      "target": "/notes/FoodCo-Farmer-Marketing-Analysis",
      "text": "notes/FoodCo Farmer Marketing Analysis"
    },
    {
      "source": "/FoodCo",
      "target": "/notes/FoodCo-Customer-Analysis",
      "text": "notes/FoodCo Customer Analysis"
    },
    {
      "source": "/FoodCo",
      "target": "/notes/CSA",
      "text": "notes/CSA"
    },
    {
      "source": "/FoodCo",
      "target": "/moc",
      "text": "moc"
    },
    {
      "source": "/Foraged",
      "target": "/notes/raw",
      "text": "notes/raw"
    },
    {
      "source": "/Georgia-Okeeffe",
      "target": "/notes/raw",
      "text": "notes/raw"
    },
    {
      "source": "/Georgia-Okeeffe",
      "target": "/notes/Art",
      "text": "notes/Art"
    },
    {
      "source": "/Georgia-Okeeffe",
      "target": "/American-Modernism",
      "text": "American Modernism"
    },
    {
      "source": "/Georgia-Okeeffe",
      "target": "/notes/frieda-kahlo",
      "text": "notes/frieda kahlo"
    },
    {
      "source": "/Georgia-Okeeffe",
      "target": "/womens-suffrage",
      "text": "women's suffrage"
    },
    {
      "source": "/Hieronymus-Bosch",
      "target": "/notes/raw",
      "text": "notes/raw"
    },
    {
      "source": "/Home",
      "target": "/notes/Polly-Labs",
      "text": "notes/Polly Labs"
    },
    {
      "source": "/Home",
      "target": "/notes/FoodCo",
      "text": "notes/FoodCo"
    },
    {
      "source": "/Home",
      "target": "/notes/Repurposing-Technology",
      "text": "notes/Repurposing Technology"
    },
    {
      "source": "/Home",
      "target": "/notes/Joblio",
      "text": "notes/Joblio"
    },
    {
      "source": "/Home",
      "target": "/google",
      "text": "google"
    },
    {
      "source": "/Home",
      "target": "/notes/People",
      "text": "notes/People"
    },
    {
      "source": "/Home",
      "target": "/family",
      "text": "family"
    },
    {
      "source": "/Home",
      "target": "/relationship",
      "text": "relationship"
    },
    {
      "source": "/Home",
      "target": "/friends",
      "text": "friends"
    },
    {
      "source": "/Home",
      "target": "/notes/cooking",
      "text": "notes/cooking"
    },
    {
      "source": "/Home",
      "target": "/notes/Fitness",
      "text": "notes/Fitness"
    },
    {
      "source": "/Home",
      "target": "/music",
      "text": "music"
    },
    {
      "source": "/Home",
      "target": "/literature",
      "text": "literature"
    },
    {
      "source": "/Home",
      "target": "/film",
      "text": "film"
    },
    {
      "source": "/Home",
      "target": "/content",
      "text": "content"
    },
    {
      "source": "/Home",
      "target": "/notes/My-Obsidian-Methodology",
      "text": "notes/My Obsidian Methodology"
    },
    {
      "source": "/Home",
      "target": "/notes/roots",
      "text": "notes/roots"
    },
    {
      "source": "/Home",
      "target": "/moc",
      "text": "moc"
    },
    {
      "source": "/How-to-figure-out-how-Farmers-Sell",
      "target": "/notes/raw",
      "text": "notes/raw"
    },
    {
      "source": "/Joblio",
      "target": "/notes/raw",
      "text": "notes/raw"
    },
    {
      "source": "/Local-Food-Marketplace",
      "target": "/notes/raw",
      "text": "notes/raw"
    },
    {
      "source": "/Local-Orbit",
      "target": "/notes/raw",
      "text": "notes/raw"
    },
    {
      "source": "/Nutrition",
      "target": "/notes/raw",
      "text": "notes/raw"
    },
    {
      "source": "/People",
      "target": "/notes/raw",
      "text": "notes/raw"
    },
    {
      "source": "/People",
      "target": "/aileen-wang",
      "text": "aileen wang"
    },
    {
      "source": "/People",
      "target": "/chiming-yang",
      "text": "chiming yang"
    },
    {
      "source": "/People",
      "target": "/kevin-yang",
      "text": "kevin yang"
    },
    {
      "source": "/People",
      "target": "/shuyuan-yang",
      "text": "shuyuan yang"
    },
    {
      "source": "/People",
      "target": "/jon-purizhansky",
      "text": "jon purizhansky"
    },
    {
      "source": "/People",
      "target": "/alina-shkolnikov",
      "text": "alina shkolnikov"
    },
    {
      "source": "/People",
      "target": "/cat-xu",
      "text": "cat xu"
    },
    {
      "source": "/Polly-Labs",
      "target": "/notes/FoodCo",
      "text": "notes/FoodCo"
    },
    {
      "source": "/Polly-Labs",
      "target": "/notes/Repurposing-Technology",
      "text": "notes/Repurposing Technology"
    },
    {
      "source": "/Polly-Labs",
      "target": "/moc",
      "text": "moc"
    },
    {
      "source": "/Red-Tomato-Food-Hub",
      "target": "/notes/raw",
      "text": "notes/raw"
    },
    {
      "source": "/",
      "target": "/notes/Polly-Labs",
      "text": "notes/Polly Labs"
    },
    {
      "source": "/",
      "target": "/notes/FoodCo",
      "text": "notes/FoodCo"
    },
    {
      "source": "/",
      "target": "/notes/Repurposing-Technology",
      "text": "notes/Repurposing Technology"
    },
    {
      "source": "/",
      "target": "/notes/Joblio",
      "text": "notes/Joblio"
    },
    {
      "source": "/",
      "target": "/google",
      "text": "google"
    },
    {
      "source": "/",
      "target": "/notes/People",
      "text": "notes/People"
    },
    {
      "source": "/",
      "target": "/family",
      "text": "family"
    },
    {
      "source": "/",
      "target": "/relationship",
      "text": "relationship"
    },
    {
      "source": "/",
      "target": "/friends",
      "text": "friends"
    },
    {
      "source": "/",
      "target": "/notes/cooking",
      "text": "notes/cooking"
    },
    {
      "source": "/",
      "target": "/notes/Fitness",
      "text": "notes/Fitness"
    },
    {
      "source": "/",
      "target": "/music",
      "text": "music"
    },
    {
      "source": "/",
      "target": "/literature",
      "text": "literature"
    },
    {
      "source": "/",
      "target": "/film",
      "text": "film"
    },
    {
      "source": "/",
      "target": "/content",
      "text": "content"
    },
    {
      "source": "/",
      "target": "/notes/My-Obsidian-Methodology",
      "text": "notes/My Obsidian Methodology"
    },
    {
      "source": "/",
      "target": "/notes/roots",
      "text": "notes/roots"
    },
    {
      "source": "/",
      "target": "/moc",
      "text": "moc"
    },
    {
      "source": "/agriculture",
      "target": "/notes/raw",
      "text": "notes/raw"
    },
    {
      "source": "/agriculture",
      "target": "/notes/FoodCo",
      "text": "notes/FoodCo"
    },
    {
      "source": "/cooking",
      "target": "/notes/raw",
      "text": "notes/raw"
    },
    {
      "source": "/frieda-kahlo",
      "target": "/notes/raw",
      "text": "notes/raw"
    },
    {
      "source": "/frieda-kahlo",
      "target": "/notes/Art",
      "text": "notes/Art"
    },
    {
      "source": "/frieda-kahlo",
      "target": "/Mexicayotl-Movement",
      "text": "Mexicayotl Movement"
    },
    {
      "source": "/frieda-kahlo",
      "target": "/notes/Hieronymus-Bosch",
      "text": "notes/Hieronymus Bosch"
    },
    {
      "source": "/notes/2023-08-17",
      "target": "/notes/raw",
      "text": "notes/raw"
    },
    {
      "source": "/notes/2023-08-18",
      "target": "/notes/raw",
      "text": "notes/raw"
    },
    {
      "source": "/notes/202308181153",
      "target": "/notes/raw",
      "text": "notes/raw"
    },
    {
      "source": "/notes/Ambrook",
      "target": "/notes/raw",
      "text": "notes/raw"
    },
    {
      "source": "/notes/Bold-Salt-Lick",
      "target": "/notes/raw",
      "text": "notes/raw"
    },
    {
      "source": "/notes/CSA",
      "target": "/notes/raw",
      "text": "notes/raw"
    },
    {
      "source": "/notes/Climate-Risk-on-Supply-Chain",
      "target": "/notes/raw",
      "text": "notes/raw"
    },
    {
      "source": "/notes/Content-List",
      "target": "/notes/raw",
      "text": "notes/raw"
    },
    {
      "source": "/notes/Content-List",
      "target": "/moc",
      "text": "moc"
    },
    {
      "source": "/notes/Conventional-vs-Controlled-Environment-Agriculture-Supply-Chains",
      "target": "/notes/raw",
      "text": "notes/raw"
    },
    {
      "source": "/notes/Conventional-vs-Controlled-Environment-Agriculture-Supply-Chains",
      "target": "/notes/agriculture",
      "text": "notes/agriculture"
    },
    {
      "source": "/notes/Farmers-Market-Management",
      "target": "/notes/raw",
      "text": "notes/raw"
    },
    {
      "source": "/notes/Fitness",
      "target": "/notes/raw",
      "text": "notes/raw"
    },
    {
      "source": "/notes/Fitness",
      "target": "/https//www.hybridcalisthenics.com/programshttps//www.hybridcalisthenics.com/programs",
      "text": "hybrid calisthenics"
    },
    {
      "source": "/notes/Food-Hub",
      "target": "/notes/raw",
      "text": "notes/raw"
    },
    {
      "source": "/notes/Food4All",
      "target": "/notes/raw",
      "text": "notes/raw"
    },
    {
      "source": "/notes/FoodCo-Competitor-Analysis",
      "target": "/notes/Seven-Suns",
      "text": "notes/Seven Suns"
    },
    {
      "source": "/notes/FoodCo-Competitor-Analysis",
      "target": "/notes/Barn2Door",
      "text": "notes/Barn2Door"
    },
    {
      "source": "/notes/FoodCo-Competitor-Analysis",
      "target": "/notes/Bold-Salt-Lick",
      "text": "notes/Bold Salt Lick"
    },
    {
      "source": "/notes/FoodCo-Competitor-Analysis",
      "target": "/notes/Eat-From-Farms",
      "text": "notes/Eat From Farms"
    },
    {
      "source": "/notes/FoodCo-Competitor-Analysis",
      "target": "/notes/Food4All",
      "text": "notes/Food4All"
    },
    {
      "source": "/notes/FoodCo-Competitor-Analysis",
      "target": "/Meicai",
      "text": "Meicai"
    },
    {
      "source": "/notes/FoodCo-Competitor-Analysis",
      "target": "/notes/Local-Orbit",
      "text": "notes/Local Orbit"
    },
    {
      "source": "/notes/FoodCo-Competitor-Analysis",
      "target": "/notes/Ambrook",
      "text": "notes/Ambrook"
    },
    {
      "source": "/notes/FoodCo-Competitor-Analysis",
      "target": "/notes/Local-Food-Marketplace",
      "text": "notes/Local Food Marketplace"
    },
    {
      "source": "/notes/FoodCo-Competitor-Analysis",
      "target": "/notes/Foraged",
      "text": "notes/Foraged"
    },
    {
      "source": "/notes/FoodCo-Customer-Analysis",
      "target": "/notes/raw",
      "text": "notes/raw"
    },
    {
      "source": "/notes/FoodCo-Distributor-Analysis",
      "target": "/notes/raw",
      "text": "notes/raw"
    },
    {
      "source": "/notes/FoodCo-Distributor-Analysis",
      "target": "/notes/Red-Tomato-Food-Hub",
      "text": "notes/Red Tomato Food Hub"
    },
    {
      "source": "/notes/FoodCo-Distributor-Analysis",
      "target": "/notes/Food-Hub",
      "text": "notes/Food Hub"
    },
    {
      "source": "/notes/FoodCo-Distributor-Analysis",
      "target": "/notes/Red-Tomato-Food-Hub",
      "text": "notes/Red Tomato Food Hub"
    },
    {
      "source": "/notes/FoodCo-Farmer-Marketing-Analysis",
      "target": "/notes/raw",
      "text": "notes/raw"
    },
    {
      "source": "/notes/FoodCo-Price-Analysis",
      "target": "/notes/raw",
      "text": "notes/raw"
    },
    {
      "source": "/notes/FoodCo",
      "target": "/notes/Polly-Labs",
      "text": "notes/Polly Labs"
    },
    {
      "source": "/notes/FoodCo",
      "target": "/notes/FoodCo-Competitor-Analysis",
      "text": "notes/FoodCo Competitor Analysis"
    },
    {
      "source": "/notes/FoodCo",
      "target": "/notes/FoodCo-Distributor-Analysis",
      "text": "notes/FoodCo Distributor Analysis"
    },
    {
      "source": "/notes/FoodCo",
      "target": "/notes/FoodCo-Price-Analysis",
      "text": "notes/FoodCo Price Analysis"
    },
    {
      "source": "/notes/FoodCo",
      "target": "/notes/FoodCo-Farmer-Marketing-Analysis",
      "text": "notes/FoodCo Farmer Marketing Analysis"
    },
    {
      "source": "/notes/FoodCo",
      "target": "/notes/FoodCo-Customer-Analysis",
      "text": "notes/FoodCo Customer Analysis"
    },
    {
      "source": "/notes/FoodCo",
      "target": "/notes/CSA",
      "text": "notes/CSA"
    },
    {
      "source": "/notes/FoodCo",
      "target": "/moc",
      "text": "moc"
    },
    {
      "source": "/notes/Foraged",
      "target": "/notes/raw",
      "text": "notes/raw"
    },
    {
      "source": "/notes/Georgia-Okeeffe",
      "target": "/notes/raw",
      "text": "notes/raw"
    },
    {
      "source": "/notes/Georgia-Okeeffe",
      "target": "/notes/Art",
      "text": "notes/Art"
    },
    {
      "source": "/notes/Georgia-Okeeffe",
      "target": "/American-Modernism",
      "text": "American Modernism"
    },
    {
      "source": "/notes/Georgia-Okeeffe",
      "target": "/notes/frieda-kahlo",
      "text": "notes/frieda kahlo"
    },
    {
      "source": "/notes/Georgia-Okeeffe",
      "target": "/womens-suffrage",
      "text": "women's suffrage"
    },
    {
      "source": "/notes/Hieronymus-Bosch",
      "target": "/notes/raw",
      "text": "notes/raw"
    },
    {
      "source": "/notes/How-to-figure-out-how-Farmers-Sell",
      "target": "/notes/raw",
      "text": "notes/raw"
    },
    {
      "source": "/notes/Joblio",
      "target": "/notes/raw",
      "text": "notes/raw"
    },
    {
      "source": "/notes/Local-Food-Marketplace",
      "target": "/notes/raw",
      "text": "notes/raw"
    },
    {
      "source": "/notes/Local-Orbit",
      "target": "/notes/raw",
      "text": "notes/raw"
    },
    {
      "source": "/notes/Nutrition",
      "target": "/notes/raw",
      "text": "notes/raw"
    },
    {
      "source": "/notes/People",
      "target": "/notes/raw",
      "text": "notes/raw"
    },
    {
      "source": "/notes/People",
      "target": "/aileen-wang",
      "text": "aileen wang"
    },
    {
      "source": "/notes/People",
      "target": "/chiming-yang",
      "text": "chiming yang"
    },
    {
      "source": "/notes/People",
      "target": "/kevin-yang",
      "text": "kevin yang"
    },
    {
      "source": "/notes/People",
      "target": "/shuyuan-yang",
      "text": "shuyuan yang"
    },
    {
      "source": "/notes/People",
      "target": "/jon-purizhansky",
      "text": "jon purizhansky"
    },
    {
      "source": "/notes/People",
      "target": "/alina-shkolnikov",
      "text": "alina shkolnikov"
    },
    {
      "source": "/notes/People",
      "target": "/cat-xu",
      "text": "cat xu"
    },
    {
      "source": "/notes/Polly-Labs",
      "target": "/notes/FoodCo",
      "text": "notes/FoodCo"
    },
    {
      "source": "/notes/Polly-Labs",
      "target": "/notes/Repurposing-Technology",
      "text": "notes/Repurposing Technology"
    },
    {
      "source": "/notes/Polly-Labs",
      "target": "/moc",
      "text": "moc"
    },
    {
      "source": "/notes/Red-Tomato-Food-Hub",
      "target": "/notes/raw",
      "text": "notes/raw"
    },
    {
      "source": "/notes/agriculture",
      "target": "/notes/raw",
      "text": "notes/raw"
    },
    {
      "source": "/notes/agriculture",
      "target": "/notes/FoodCo",
      "text": "notes/FoodCo"
    },
    {
      "source": "/notes/cooking",
      "target": "/notes/raw",
      "text": "notes/raw"
    },
    {
      "source": "/notes/frieda-kahlo",
      "target": "/notes/raw",
      "text": "notes/raw"
    },
    {
      "source": "/notes/frieda-kahlo",
      "target": "/notes/Art",
      "text": "notes/Art"
    },
    {
      "source": "/notes/frieda-kahlo",
      "target": "/Mexicayotl-Movement",
      "text": "Mexicayotl Movement"
    },
    {
      "source": "/notes/frieda-kahlo",
      "target": "/notes/Hieronymus-Bosch",
      "text": "notes/Hieronymus Bosch"
    },
    {
      "source": "/notes/raw",
      "target": "/notes/raw",
      "text": "notes/raw"
    },
    {
      "source": "/notes/roots",
      "target": "/notes/raw",
      "text": "notes/raw"
    },
    {
      "source": "/notes/roots",
      "target": "/notes/agriculture",
      "text": "notes/agriculture"
    },
    {
      "source": "/raw",
      "target": "/notes/raw",
      "text": "notes/raw"
    },
    {
      "source": "/roots",
      "target": "/notes/raw",
      "text": "notes/raw"
    },
    {
      "source": "/roots",
      "target": "/notes/agriculture",
      "text": "notes/agriculture"
    }
  ]
}